eventsocket.py
freeswitch_eventsocket-0.5.dev.dist-info/DESCRIPTION.rst
freeswitch_eventsocket-0.5.dev.dist-info/METADATA
freeswitch_eventsocket-0.5.dev.dist-info/metadata.json
freeswitch_eventsocket-0.5.dev.dist-info/RECORD
freeswitch_eventsocket-0.5.dev.dist-info/top_level.txt
freeswitch_eventsocket-0.5.dev.dist-info/WHEEL
