Metadata-Version: 2.0
Name: freeswitch-eventsocket
Version: 0.5.dev
Summary: This is a work in progress abstraction class to handle freeswitch's eventsocket command lines.
Home-page: https://github.com/fernandoflorez/freeswitch-eventsocket
Author: Fernando Flórez
Author-email: fernando@funciton.com
License: http://www.apache.org/licenses/LICENSE-2.0
Platform: UNKNOWN
